AUTHORS
LICENSE
LICENSE-3RD-PARTY
MANIFEST.in
README.rst
setup.cfg
setup.py
contact_form_bootstrap/__init__.py
contact_form_bootstrap/templates/contact_form/base.html
contact_form_bootstrap/templates/contact_form/contact_form.html
contact_form_bootstrap/templates/contact_form/contact_form.txt
contact_form_bootstrap/templates/contact_form/contact_form_sent.html
contact_form_bootstrap/templates/contact_form/contact_form_subject.txt
django_contact_form_bootstrap.egg-info/PKG-INFO
django_contact_form_bootstrap.egg-info/SOURCES.txt
django_contact_form_bootstrap.egg-info/dependency_links.txt
django_contact_form_bootstrap.egg-info/not-zip-safe
django_contact_form_bootstrap.egg-info/requires.txt
django_contact_form_bootstrap.egg-info/top_level.txt