Metadata-Version: 1.1
Name: django-contact-form-bootstrap
Version: 0.1a1
Summary: Twitter Bootstrap Layout for Django Contact Form
Home-page: https://bitbucket.org/cschur/django-contact-form-bootstrap
Author: Chris Schur
Author-email: chris.schur@gmx.de
License: BSD License
Keywords: django,contact,Twitter,Bootstrap,website
Platform: OS Independent
Classifier: Development Status :: 3 - Alpha
Classifier: Environment :: Web Environment
Classifier: Framework :: Django
Classifier: Intended Audience :: Developers
Classifier: License :: OSI Approved :: BSD License
Classifier: Operating System :: OS Independent
Classifier: Programming Language :: Python
Classifier: Programming Language :: Python :: 2.7
Classifier: Programming Language :: Python :: 3.3
Classifier: Programming Language :: Python :: 3.4
Classifier: Topic :: Internet :: WWW/HTTP
Classifier: Topic :: Internet :: WWW/HTTP :: Dynamic Content
Classifier: Topic :: Internet :: WWW/HTTP :: WSGI
Classifier: Topic :: Software Development :: Libraries :: Python Modules
